MANIFEST.in
README
setup.cfg
setup.py
livestatus_service/__init__.py
livestatus_service/configuration.py
livestatus_service/dispatcher.py
livestatus_service/icinga.py
livestatus_service/livestatus.py
livestatus_service/livestatus_service.conf
livestatus_service/livestatus_service.wsgi
livestatus_service/webapp.py
livestatus_service.egg-info/PKG-INFO
livestatus_service.egg-info/SOURCES.txt
livestatus_service.egg-info/dependency_links.txt
livestatus_service.egg-info/requires.txt
livestatus_service.egg-info/top_level.txt
livestatus_service.egg-info/zip-safe
livestatus_service/templates/index.html
livestatus_service/templates/template.html