Metadata-Version: 1.1
Name: livestatus-service
Version: 0.3.1
Summary: Exposes MK livestatus to the outside world over HTTP
Home-page: https://github.com/ImmobilienScout24/livestatus_service
Author: Marcel Wolf, Maximilien Riehl
Author-email: marcel.wolf@immobilienscout24.de, maximilien.riehl@gmail.com
License: MIT
Platform: UNKNOWN
Classifier: Development Status :: 4 - Beta
Classifier: Environment :: Web Environment
Classifier: Intended Audience :: Developers
Classifier: Intended Audience :: System Administrators
Classifier: Programming Language :: Python
Classifier: Natural Language :: English
Classifier: Operating System :: POSIX :: Linux
Classifier: Topic :: System :: Monitoring
Classifier: Programming Language :: Python :: 2.6
Classifier: Programming Language :: Python :: 2.7
Classifier: Programming Language :: Python :: 3
Classifier: License :: OSI Approved :: MIT License
Classifier: Programming Language :: Python :: Implementation :: CPython
Classifier: Programming Language :: Python :: Implementation :: Jython
Classifier: Programming Language :: Python :: Implementation :: PyPy
